{
  "key": "plugin_content_manager_configuration_content_types::api::p2p.p2p",
  "value": {
    "uid": "api::p2p.p2p",
    "settings": {
      "bulkable": true,
      "filterable": true,
      "searchable": true,
      "pageSize": 50,
      "mainField": "name",
      "defaultSortBy": "createdAt",
      "defaultSortOrder": "ASC"
    },
    "metadatas": {
      "id": {
        "edit": {},
        "list": {
          "label": "id",
          "searchable": true,
          "sortable": true
        }
      },
      "name": {
        "edit": {
          "label": "name",
          "description": "",
          "placeholder": "",
          "visible": true,
          "editable": true
        },
        "list": {
          "label": "name",
          "searchable": true,
          "sortable": true
        }
      },
      "info": {
        "edit": {
          "label": "info",
          "description": "",
          "placeholder": "",
          "visible": true,
          "editable": true
        },
        "list": {
          "label": "info",
          "searchable": true,
          "sortable": true
        }
      },
      "status": {
        "edit": {
          "label": "status",
          "description": "",
          "placeholder": "",
          "visible": true,
          "editable": true
        },
        "list": {
          "label": "status",
          "searchable": true,
          "sortable": true
        }
      },
      "dirs": {
        "edit": {
          "label": "dirs",
          "description": "",
          "placeholder": "",
          "visible": true,
          "editable": true
        },
        "list": {
          "label": "dirs",
          "searchable": false,
          "sortable": false
        }
      },
      "regulationCodes": {
        "edit": {
          "label": "regulationCodes",
          "description": "",
          "placeholder": "",
          "visible": true,
          "editable": true
        },
        "list": {
          "label": "regulationCodes",
          "searchable": false,
          "sortable": false
        }
      },
      "locations": {
        "edit": {
          "label": "locations",
          "description": "",
          "placeholder": "",
          "visible": true,
          "editable": true
        },
        "list": {
          "label": "locations",
          "searchable": false,
          "sortable": false
        }
      },
      "uid": {
        "edit": {
          "label": "uid",
          "description": "",
          "placeholder": "",
          "visible": true,
          "editable": true
        },
        "list": {
          "label": "uid",
          "searchable": true,
          "sortable": true
        }
      },
      "admin_comment": {
        "edit": {
          "label": "admin_comment",
          "description": "",
          "placeholder": "",
          "visible": true,
          "editable": true
        },
        "list": {
          "label": "admin_comment",
          "searchable": true,
          "sortable": true
        }
      },
      "telegram": {
        "edit": {
          "label": "telegram",
          "description": "",
          "placeholder": "",
          "visible": true,
          "editable": true
        },
        "list": {
          "label": "telegram",
          "searchable": false,
          "sortable": false
        }
      },
      "createdAt": {
        "edit": {
          "label": "createdAt",
          "description": "",
          "placeholder": "",
          "visible": false,
          "editable": true
        },
        "list": {
          "label": "createdAt",
          "searchable": true,
          "sortable": true
        }
      },
      "updatedAt": {
        "edit": {
          "label": "updatedAt",
          "description": "",
          "placeholder": "",
          "visible": false,
          "editable": true
        },
        "list": {
          "label": "updatedAt",
          "searchable": true,
          "sortable": true
        }
      },
      "createdBy": {
        "edit": {
          "label": "createdBy",
          "description": "",
          "placeholder": "",
          "visible": false,
          "editable": true,
          "mainField": "firstname"
        },
        "list": {
          "label": "createdBy",
          "searchable": true,
          "sortable": true
        }
      },
      "updatedBy": {
        "edit": {
          "label": "updatedBy",
          "description": "",
          "placeholder": "",
          "visible": false,
          "editable": true,
          "mainField": "firstname"
        },
        "list": {
          "label": "updatedBy",
          "searchable": true,
          "sortable": true
        }
      }
    },
    "layouts": {
      "list": [
        "name",
        "uid",
        "status",
        "id"
      ],
      "edit": [
        [
          {
            "name": "name",
            "size": 6
          }
        ],
        [
          {
            "name": "info",
            "size": 6
          },
          {
            "name": "status",
            "size": 6
          }
        ],
        [
          {
            "name": "dirs",
            "size": 12
          }
        ],
        [
          {
            "name": "regulationCodes",
            "size": 12
          }
        ],
        [
          {
            "name": "locations",
            "size": 12
          }
        ],
        [
          {
            "name": "uid",
            "size": 6
          },
          {
            "name": "admin_comment",
            "size": 6
          }
        ],
        [
          {
            "name": "telegram",
            "size": 12
          }
        ]
      ]
    }
  },
  "type": "object",
  "environment": null,
  "tag": null
}